sqlf/__init__.py
sqlf/_sqlf.py
sqlf/_udf_cryptography.py
sqlf/_udf_encoding.py
sqlf/_udf_serialisation.py
sqlf/_udf_text.py
sqlf-0.2.9.dist-info/METADATA
sqlf-0.2.9.dist-info/RECORD
sqlf-0.2.9.dist-info/WHEEL
sqlf-0.2.9.dist-info/top_level.txt
