Metadata-Version: 2.1
Name: sqlf
Version: 0.2.9
Summary: SQL in Python __doc__-strings as an alternative to ORMs
Home-page: https://github.com/digitalmensch/sqlf
Author: Digitalmensch
Author-email: contact@digitalmensch.ch
License: MIT license
Keywords: sqlf,sql,sqlite,function,orm
Platform: UNKNOWN
Classifier: Development Status :: 2 - Pre-Alpha
Classifier: Intended Audience :: Developers
Classifier: License :: OSI Approved :: MIT License
Classifier: Natural Language :: English
Classifier: Programming Language :: Python :: 3
Classifier: Programming Language :: Python :: 3.4
Classifier: Programming Language :: Python :: 3.5
Classifier: Programming Language :: Python :: 3.6
Classifier: Programming Language :: Python :: 3 :: Only
Classifier: Topic :: Database :: Front-Ends
Classifier: Operating System :: OS Independent
Requires-Dist: apsw
Requires-Dist: base91
Requires-Dist: cbor2
Requires-Dist: typeguard
